Workbook

Sheet Ведомость объёмов
A1: Ведомость объёмов работ. Шифр 2026-МОС40-ИЗ. Объёмы по расчётной модели; уточняются в РД.
A3: № | B3: Раздел | C3: Наименование работ | D3: Ед. | E3: Зона I (42 м) | F3: Зона II (24 м) | G3: Зона III (33 м) | H3: Всего
A4: 1 | B4: 0. Подготовка | C4: Доизыскания: ИГИ (4 скв. 25–30 м, CD/CU, CPTU), гидрометеорология, геодезия, обследование | D4: компл. | E4: 1 | F4: 0 | G4: 0 | H4: =SUM(E4:G4)
A5: 2 | B5: 0. Подготовка | C5: Рабочая документация (организация — член СРО), авторский надзор | D5: компл. | E5: 1 | F5: 0 | G5: 0 | H5: =SUM(E5:G5)
A6: 3 | B6: 0. Подготовка | C6: Разрешительная документация (земля, водопользование, Росрыболовство) | D6: компл. | E6: 1 | F6: 0 | G6: 0 | H6: =SUM(E6:G6)
A7: 4 | B7: 0. Подготовка | C7: Мобилизация оборудования струйной цементации, временный съезд и рабочая площадка на склоне | D7: компл. | E7: 1 | F7: 0.25 | G7: 0.25 | H7: =SUM(E7:G7)
A8: 5 | B8: 0. Подготовка | C8: Противоаварийные меры: ограждение, знаки, временный водоотвод | D8: компл. | E8: 1 | F8: 0 | G8: 0 | H8: =SUM(E8:G8)
A9: 6 | B9: 1. Демонтаж | C9: Демонтаж обзорной площадки (металлокаркас ≈ 8 т, настил) | D9: компл. | E9: 1 | F9: 0 | G9: 0 | H9: =SUM(E9:G9)
A10: 7 | B10: 1. Демонтаж | C10: Разборка ж/б стен W1–W4, бордюров с вывозом | D10: м³ | E10: 33 | F10: 6 | G10: 10 | H10: =SUM(E10:G10)
A11: 8 | B11: 2. Земляные работы | C11: Срезка грунта на склоне с вывозом за пределы водоохранной зоны | D11: м³ | E11: 774.6 | F11: 160.8 | G11: 211.2 | H11: =SUM(E11:G11)
A12: 9 | B12: 2. Земляные работы | C12: Подсыпка бермы с уплотнением Kcom ≥ 0,95 | D12: м³ | E12: 213 | F12: 26.4 | G12: 171.6 | H12: =SUM(E12:G12)
A13: 10 | B13: 3. Грунтоцементные рёбра | C13: Колонны струйной цементации Jet-2 Ø1,0 м (с цементом, вывоз шлама) | D13: п. м | E13: 2608 | F13: 1473 | G13: 1915 | H13: =SUM(E13:G13)
A14: 11 | B14: 3. Грунтоцементные рёбра | C14: Пробные колонны (3 шт.), откопка, кернение, испытания | D14: компл. | E14: 1 | F14: 0 | G14: 0 | H14: =SUM(E14:G14)
A15: 12 | B15: 3. Грунтоцементные рёбра | C15: Армирование трубой 146×8 (поставка и погружение) | D15: т | E15: 40.09 | F15: 22.64 | G15: 29.42 | H15: =SUM(E15:G15)
... A31: 28 | B31: 10. Мониторинг | C31: Наблюдения и отчёты (строительство + 2 года) | D31: компл. | E31: 0.6 | F31: 0.2 | G31: 0.2 | H31: =SUM(E31:G31)

Sheet Смета укрупнённая
A1: Укрупнённый расчёт стоимости (ориентировочно), руб., цены IV кв. 2026 г., без НДС. Точность ±30 %.
A2: Расценки — по открытым рыночным данным 2025–2026 гг. и расчёту по материалоёмкости (см. «Обоснование стоимости»); перед договорами — КП подрядчиков.
A3: № | B3: Раздел | C3: Наименование | D3: Ед. | E3: Кол-во всего | F3: Цена мин | G3: Цена макс | H3: Сумма мин | I3: Сумма макс | J3: Зона I мин | K3: Зона I макс | L3: Примечание
A4: 1 | B4: 0. Подготовка | C4: Доизыскания: ИГИ (4 скв. 25–30 м, CD/CU, CPTU), гидрометеорология, геодезия, обследование | D4: компл. | E4: ='Ведомость объёмов'!H4 | F4: 1500000 | G4: 2500000 | H4: =E4*F4 | I4: =E4*G4 | J4: ='Ведомость объёмов'!E4*F4 | K4: ='Ведомость объёмов'!E4*G4 | L4: раздел 15 ПЗ
A5: 2 | B5: 0. Подготовка | C5: Рабочая документация (организация — член СРО), авторский надзор | D5: компл. | E5: ='Ведомость объёмов'!H5 | F5: 2500000 | G5: 4000000 | H5: =E5*F5 | I5: =E5*G5 | J5: ='Ведомость объёмов'!E5*F5 | K5: ='Ведомость объёмов'!E5*G5 | L5: ≈ 3–5 % стоимости работ
A6: 3 | B6: 0. Подготовка | C6: Разрешительная документация (земля, водопользование, Росрыболовство) | D6: компл. | E6: ='Ведомость объёмов'!H6 | F6: 300000 | G6: 900000 | H6: =E6*F6 | I6: =E6*G6 | J6: ='Ведомость объёмов'!E6*F6 | K6: ='Ведомость объёмов'!E6*G6 | L6: раздел 13 ПЗ
A7: 4 | B7: 0. Подготовка | C7: Мобилизация оборудования струйной цементации, временный съезд и рабочая площадка на склоне | D7: компл. | E7: ='Ведомость объёмов'!H7 | F7: 1500000 | G7: 3000000 | H7: =E7*F7 | I7: =E7*G7 | J7: ='Ведомость объёмов'!E7*F7 | K7: ='Ведомость объёмов'!E7*G7 | L7: зоны II–III — 25 %
A8: 5 | B8: 0. Подготовка | C8: Противоаварийные меры: ограждение, знаки, временный водоотвод | D8: компл. | E8: ='Ведомость объёмов'!H8 | F8: 250000 | G8: 500000 | H8: =E8*F8 | I8: =E8*G8 | J8: ='Ведомость объёмов'!E8*F8 | K8: ='Ведомость объёмов'!E8*G8
A9: 6 | B9: 1. Демонтаж | C9: Демонтаж обзорной площадки (металлокаркас ≈ 8 т, настил) | D9: компл. | E9: ='Ведомость объёмов'!H9 | F9: 300000 | G9: 600000 | H9: =E9*F9 | I9: =E9*G9 | J9: ='Ведомость объёмов'!E9*F9 | K9: ='Ведомость объёмов'!E9*G9
A10: 7 | B10: 1. Демонтаж | C10: Разборка ж/б стен W1–W4, бордюров с вывозом | D10: м³ | E10: ='Ведомость объёмов'!H10 | F10: 7000 | G10: 12000 | H10: =E10*F10 | I10: =E10*G10 | J10: ='Ведомость объёмов'!E10*F10 | K10: ='Ведомость объёмов'!E10*G10
A11: 8 | B11: 2. Земляные работы | C11: Срезка грунта на склоне с вывозом за пределы водоохранной зоны | D11: м³ | E11: ='Ведомость объёмов'!H11 | F11: 900 | G11: 1500 | H11: =E11*F11 | I11: =E11*G11 | J11: ='Ведомость объёмов'!E11*F11 | K11: ='Ведомость объёмов'!E11*G11
A12: 9 | B12: 2. Земляные работы | C12: Подсыпка бермы с уплотнением Kcom ≥ 0,95 | D12: м³ | E12: ='Ведомость объёмов'!H12 | F12: 600 | G12: 1000 | H12: =E12*F12 | I12: =E12*G12 | J12: ='Ведомость объёмов'!E12*F12 | K12: ='Ведомость объёмов'!E12*G12
A13: 10 | B13: 3. Грунтоцементные рёбра | C13: Колонны струйной цементации Jet-2 Ø1,0 м (с цементом, вывоз шлама) | D13: п. м | E13: ='Ведомость объёмов'!H13 | F13: 6500 | G13: 10500 | H13: =E13*F13 | I13: =E13*G13 | J13: ='Ведомость объёмов'!E13*F13 | K13: ='Ведомость объёмов'!E13*G13 | L13: главная статья
A14: 11 | B14: 3. Грунтоцементные рёбра | C14: Пробные колонны (3 шт.), откопка, кернение, испытания | D14: компл. | E14: ='Ведомость объёмов'!H14 | F14: 600000 | G14: 1000000 | H14: =E14*F14 | I14: =E14*G14 | J14: ='Ведомость объёмов'!E14*F14 | K14: ='Ведомость объёмов'!E14*G14
A15: 12 | B15: 3. Грунтоцементные рёбра | C15: Армирование трубой 146×8 (поставка и погружение) | D15: т | E15: ='Ведомость объёмов'!H15 | F15: 120000 | G15: 160000 | H15: =E15*F15 | I15: =E15*G15 | J15: ='Ведомость объёмов'!E15*F15 | K15: ='Ведомость объёмов'!E15*G15 | L15: оценка, уточнить КП
A16: 13 | B16: 3. Грунтоцементные рёбра | C16: Контроль качества: керн 2 % колонн, лаборатория | D16: компл. | E16: ='Ведомость объёмов'!H16 | F16: 600000 | G16: 900000 | H16: =E16*F16 | I16: =E16*G16 | J16: ='Ведомость объёмов'!E16*F16 | K16: ='Ведомость объёмов'!E16*G16
A17: 14 | B17: 4. Балка | C17: Обвязочная ж/б балка 1,0×0,6 м B30 (арматура, опалубка) | D17: м³ | E17: ='Ведомость объёмов'!H17 | F17: 30000 | G17: 45000 | H17: =E17*F17 | I17: =E17*G17 | J17: ='Ведомость объёмов'!E17*F17 | K17: ='Ведомость объёмов'!E17*G17
A18: 15 | B18: 5. Габионы и крепление | C18: Габионы коробчатые с камнем, сетка Zn-Al+ПВХ | D18: м³ | E18: ='Ведомость объёмов'!H18 | F18: 8000 | G18: 12000 | H18: =E18*F18 | I18: =E18*G18 | J18: ='Ведомость объёмов'!E18*F18 | K18: ='Ведомость объёмов'!E18*G18
A19: 16 | B19: 5. Габионы и крепление | C19: Матрацы Рено 0,3 м на геотекстиле (вкл. подводную часть, фартук) | D19: м² | E19: ='Ведомость объёмов'!H19 | F19: 2800 | G19: 4500 | H19: =E19*F19 | I19: =E19*G19 | J19: ='Ведомость объёмов'!E19*F19 | K19: ='Ведомость объёмов'!E19*G19
A20: 17 | B20: 5. Габионы и крепление | C20: Щебёночная подушка, дренирующая засыпка за габионами с дреной Ø110 | D20: п. м | E20: ='Ведомость объёмов'!H20 | F20: 4000 | G20: 6500 | H20: =E20*F20 | I20: =E20*G20 | J20: ='Ведомость объёмов'!E20*F20 | K20: ='Ведомость объёмов'!E20*G20
A21: 18 | B21: 6. Дренаж | C21: Перехватывающий дренаж Д-1 (траншея 3,2 м, щебень, труба Ø160) | D21: п. м | E21: ='Ведомость объёмов'!H21 | F21: 9000 | G21: 15000 | H21: =E21*F21 | I21: =E21*G21 | J21: ='Ведомость объёмов'!E21*F21 | K21: ='Ведомость объёмов'!E21*G21
A22: 19 | B22: 6. Дренаж | C22: Колодцы ДК Ø1000 полимерные | D22: шт. | E22: ='Ведомость объёмов'!H22 | F22: 90000 | G22: 150000 | H22: =E22*F22 | I22: =E22*G22 | J22: ='Ведомость объёмов'!E22*F22 | K22: ='Ведомость объёмов'!E22*G22
A23: 20 | B23: 6. Дренаж | C23: Выпуски ПНД Ø160–200 с оголовками | D23: шт. | E23: ='Ведомость объёмов'!H23 | F23: 150000 | G23: 250000 | H23: =E23*F23 | I23: =E23*G23 | J23: ='Ведомость объёмов'!E23*F23 | K23: ='Ведомость объёмов'!E23*G23
A24: 21 | B24: 6. Дренаж | C24: Горизонтальные дренажные скважины Ø108, L = 15,5 м | D24: п. м | E24: ='Ведомость объёмов'!H24 | F24: 2500 | G24: 4000 | H24: =E24*F24 | I24: =E24*G24 | J24: ='Ведомость объёмов'!E24*F24 | K24: ='Ведомость объёмов'!E24*G24
A25: 22 | B25: 7. Водоотвод | C25: Лоток DN200 с решётками по бровке, подключение водостоков | D25: п. м | E25: ='Ведомость объёмов'!H25 | F25: 4500 | G25: 7000 | H25: =E25*F25 | I25: =E25*G25 | J25: ='Ведомость объёмов'!E25*F25 | K25: ='Ведомость объёмов'!E25*G25
A26: 23 | B26: 8. Откосы | C26: Объёмная георешётка h = 150 мм, анкеры, растительный грунт, посев | D26: м² | E26: ='Ведомость объёмов'!H26 | F26: 800 | G26: 1300 | H26: =E26*F26 | I26: =E26*G26 | J26: ='Ведомость объёмов'!E26*F26 | K26: ='Ведомость объёмов'!E26*G26
A27: 24 | B27: 8. Откосы | C27: Посадка кустарника (ива, кизильник, спирея) | D27: шт. | E27: ='Ведомость объёмов'!H27 | F27: 600 | G27: 1200 | H27: =E27*F27 | I27: =E27*G27 | J27: ='Ведомость объёмов'!E27*F27 | K27: ='Ведомость объёмов'!E27*G27
A28: 25 | B28: 9. Благоустройство | C28: Лестница металлическая на винтовых сваях с площадками | D28: компл. | E28: ='Ведомость объёмов'!H28 | F28: 1200000 | G28: 2000000 | H28: =E28*F28 | I28: =E28*G28 | J28: ='Ведомость объёмов'!E28*F28 | K28: ='Ведомость объёмов'!E28*G28 | L28: на устойчивость не влияет
A29: 26 | B29: 10. Мониторинг | C29: Инклинометрические скважины 22 м | D29: шт. | E29: ='Ведомость объёмов'!H29 | F29: 150000 | G29: 250000 | H29: =E29*F29 | I29: =E29*G29 | J29: ='Ведомость объёмов'!E29*F29 | K29: ='Ведомость объёмов'!E29*G29
A30: 27 | B30: 10. Мониторинг | C30: Пьезометры | D30: шт. | E30: ='Ведомость объёмов'!H30 | F30: 80000 | G30: 120000 | H30: =E30*F30 | I30: =E30*G30 | J30: ='Ведомость объёмов'!E30*F30 | K30: ='Ведомость объёмов'!E30*G30
A31: 28 | B31: 10. Мониторинг | C31: Наблюдения и отчёты (строительство + 2 года) | D31: компл. | E31: ='Ведомость объёмов'!H31 | F31: 1000000 | G31: 1800000 | H31: =E31*F31 | I31: =E31*G31 | J31: ='Ведомость объёмов'!E31*F31 | K31: ='Ведомость объёмов'!E31*G31
C32: Итого | H32: =SUM(H4:H31) | I32: =SUM(I4:I31) | J32: =SUM(J4:J31) | K32: =SUM(K4:K31)
C33: Непредвиденные работы и затраты, 10 % | H33: =H32*0.1 | I33: =I32*0.1 | J33: =J32*0.1 | K33: =K32*0.1
C34: ВСЕГО без НДС | H34: =H32+H33 | I34: =I32+I33 | J34: =J32+J33 | K34: =K32+K33
C35: НДС — по ставке, действующей на дату договора

Sheet Очерёдность
A1: Рекомендуемая очерёдность финансирования (млн руб. без НДС, с непредвиденными 10 %, ориентировочно)
A3: Этап | B3: Состав | C3: Мин | D3: Макс
A4: Этап 0 + 1 (зона I, ≈ 42 м) | B4: Противоаварийные меры, доизыскания, РД, разрешения; демонтаж, дренаж, ГЦК зоны I, балка, габионы, Рено, откосы, лестница, мониторинг | C4: 43.3 | D4: 69.7
A5: Этап 2 (зоны II–III, ≈ 57 м) | B5: После доизысканий и 1 года мониторинга; возможна оптимизация ГЦК на 30–50 % | C5: 44.3 | D5: 69.6
A6: Всего | C6: 87.6 | D6: 139.3

Sheet Варианты
A1: Варианты по бюджету (ориентировочно, млн руб. без НДС, с непредвиденными)
A3: Вариант | B3: Состав | C3: Мин | D3: Макс | E3: Запас устойчивости | F3: Что остаётся
A4: D0. Первоочередное (план 2026-МОС40-ПМ) | B4: отвод воды с крыш и двора (коллектор и закрытый выпуск), разборка аварийной площадки, ограждение на винтовых сваях, реперы, марки, маяки, наблюдательные скважины; стоимость — по плану 2026-МОС40-ПМ | C4: 0.8 | D4: 1.4 | E4: весной ориентировочно не опускается до 0,87–0,97 | F4: склон остаётся аварийным (ниже нормы 1,15)
A5: D. Неотложный этап: вода + данные | B5: первоочередное + доизыскания, перехватывающий дренаж вдоль двора, датчики сдвига и уровня воды, наблюдения 2 года | C5: 7.9 | D5: 13.6 | E5: весной запас не опускается до 0,87–0,97, остаётся ≈ 0,93–1,01 | F5: ниже нормы 1,15; зато появляются данные для уменьшения объёма рёбер
A6: C. Без подземных рёбер (вариант 1 ПЗ) | B6: неотложный этап + разборка стен, срезка и берма, горизонтальные дрены, габионы и матрацы у воды, откосы | C6: 25.1 | D6: 41.4 | E6: 1,00–1,05 | F6: ниже нормы 1,15: риск оползня снижается, но не устраняется
A7: B. Первая очередь: участок у дома ≈ 42 м | B7: полный набор работ только на аварийном участке (разрезы А-А и Г-Г) | C7: 43.3 | D7: 69.7 | E7: 1,25–1,27 на участке у дома | F7: участки II–III (≈ 57 м) остаются с запасом 1,00–1,01
A8: A. Полная защита всего склона ≈ 100 м | B8: все работы проекта по всему фронту | C8: 87.6 | D8: 139.3 | E8: 1,25–1,31 (при землетрясении 7 баллов 1,09–1,13) | F8: норма выполняется
